{
  "type": "minecraft:crafting_shaped",
  "category": "misc",
  "key": {
    "C": {
      "item": "enderio:octadic_capacitor"
    },
    "F": {
      "tag": "c:glass_blocks/dark_fused_quartz"
    },
    "G": {
      "item": "minecraft:glowstone"
    },
    "I": {
      "tag": "c:ingots/vibrant_alloy"
    },
    "P": {
      "item": "enderio:photovoltaic_plate"
    },
    "S": {
      "item": "enderio:pulsating_photovoltaic_module"
    }
  },
  "pattern": [
    "IFI",
    "PGP",
    "CSC"
  ],
  "result": {
    "count": 1,
    "id": "enderio:vibrant_photovoltaic_module"
  }
}