{
  "type": "minecraft:crafting_shapeless",
  "ingredients": [
    {
      "tag": "enderio:clear_glass_da"
    },
    {
      "tag": "enderio:clear_glass_da"
    },
    {
      "tag": "enderio:clear_glass_da"
    },
    {
      "tag": "enderio:clear_glass_da"
    },
    {
      "tag": "enderio:clear_glass_da"
    },
    {
      "tag": "enderio:clear_glass_da"
    },
    {
      "tag": "enderio:clear_glass_da"
    },
    {
      "tag": "enderio:clear_glass_da"
    },
    {
      "tag": "forge:dyes/yellow"
    }
  ],
  "result": {
    "item": "enderio:clear_glass_da_yellow",
    "count": 8
  }
}