{
  "parent": "minecraft:recipes/root",
  "criteria": {
    "has_ingredien": {
      "conditions": {
        "items": [
          {
            "items": [
              "enderio:vibrant_alloy_nugget"
            ]
          }
        ]
      },
      "trigger": "minecraft:inventory_changed"
    },
    "has_the_recipe": {
      "conditions": {
        "recipe": "enderio:vibrant_crystal"
      },
      "trigger": "minecraft:recipe_unlocked"
    }
  },
  "requirements": [
    [
      "has_ingredien",
      "has_the_recipe"
    ]
  ],
  "rewards": {
    "recipes": [
      "enderio:vibrant_crystal"
    ]
  }
}